examples/file.vh
//==============================================================================
// Module: cordic
// Description: CORDIC (COordinate Rotation DIgital Computer) algorithm
//              implementation for computing sine and cosine of input angle
// Algorithm: Rotation mode CORDIC with 15 iterations
// Format: Q1.14 fixed-point representation
// Author: Chia-Hung Hsiao
// Date: 2025/9/1
//==============================================================================
module cordic #(
    parameter WL = 16,      // Word length
    parameter FL = 14,      // Fractional length
    parameter N_ITER = 15   // Number of iterations
)(
    input  wire                clk,        // Clock signal
    input  wire                rst_n,      // Active-low reset
    input  wire                start,      // Start computation
    input  wire signed [WL-1:0] angle_in,  // Input angle in radians, Q1.14, range: [-π/2, π/2]
    output reg  signed [WL-1:0] cos_out,   // Cosine output, Q1.14
    output reg  signed [WL-1:0] sin_out,   // Sine output, Q1.14
    output reg                 done        // Computation complete flag
);

    //--------------------------------------------------------------------------
    // Arctan lookup table
    // Stores precomputed arctan(2^-i) values in Q1.14 format
    //--------------------------------------------------------------------------
    wire signed [WL-1:0] atan_table [0:N_ITER-1];

    //--------------------------------------------------------------------------
    // Internal registers
    //--------------------------------------------------------------------------
    reg signed [WL-1:0] x;              // X coordinate accumulator
    reg signed [WL-1:0] y;              // Y coordinate accumulator
    reg signed [WL-1:0] z;              // Angle accumulator
    reg [4:0] i;                        // Iteration counter
    reg [1:0] state, next_state;        // FSM state registers

    //--------------------------------------------------------------------------
    // State machine definitions
    //--------------------------------------------------------------------------
    localparam IDLE   = 2'd0;
    localparam ROTATE = 2'd1;
    localparam DONE   = 2'd2;

    //--------------------------------------------------------------------------
    // CORDIC scaling factor constant
    // K ≈ 0.60725 (product of cos(arctan(2^-i)) for i=0 to infinity)
    // Represented in Q1.14 format: 0.60725 × 2^14 ≈ 9949
    //--------------------------------------------------------------------------
    localparam signed [WL-1:0] K = 16'sd9949;

    //--------------------------------------------------------------------------
    // FSM state register
    // Sequential logic for state transitions
    //--------------------------------------------------------------------------
    always @(posedge clk or negedge rst_n) begin
        if (!rst_n)
            state <= IDLE;
        else
            state <= next_state;
    end

    //--------------------------------------------------------------------------
    // FSM next state logic
    // Combinational logic for determining next state
    //--------------------------------------------------------------------------
    always @(*) begin
        case (state)
            IDLE:    next_state = start ? ROTATE : IDLE;
            ROTATE:  next_state = (i == N_ITER-1) ? DONE : ROTATE;
            DONE:    next_state = IDLE;
            default: next_state = IDLE;
        endcase
    end

    // Initialize arctan lookup table (Q1.14 format)
    assign atan_table[0]  = 16'sb0011_0010_0100_0100;   // atan(2^-0)  = 45.000° ≈ 0.78539 rad
    assign atan_table[1]  = 16'sb0001_1101_1010_1100;   // atan(2^-1)  = 26.565° ≈ 0.46365 rad
    assign atan_table[2]  = 16'sb0000_1111_1010_1110;   // atan(2^-2)  = 14.036° ≈ 0.24498 rad
    assign atan_table[3]  = 16'sb0000_0111_1111_0101;   // atan(2^-3)  =  7.125° ≈ 0.12435 rad
    assign atan_table[4]  = 16'sb0000_0011_1111_1111;   // atan(2^-4)  =  3.576° ≈ 0.06241 rad
    assign atan_table[5]  = 16'sb0000_0010_0000_0000;   // atan(2^-5)  =  1.790° ≈ 0.03123 rad
    assign atan_table[6]  = 16'sb0000_0001_0000_0000;   // atan(2^-6)  =  0.895° ≈ 0.01562 rad
    assign atan_table[7]  = 16'sb0000_0000_1000_0000;   // atan(2^-7)  =  0.448° ≈ 0.00781 rad
    assign atan_table[8]  = 16'sb0000_0000_0100_0000;   // atan(2^-8)  =  0.224° ≈ 0.00391 rad
    assign atan_table[9]  = 16'sb0000_0000_0010_0000;   // atan(2^-9)  =  0.112° ≈ 0.00195 rad
    assign atan_table[10] = 16'sb0000_0000_0001_0000;   // atan(2^-10) =  0.056° ≈ 0.00098 rad
    assign atan_table[11] = 16'sb0000_0000_0000_1000;   // atan(2^-11) =  0.028° ≈ 0.00049 rad
    assign atan_table[12] = 16'sb0000_0000_0000_0100;   // atan(2^-12) =  0.014° ≈ 0.00024 rad
    assign atan_table[13] = 16'sb0000_0000_0000_0010;   // atan(2^-13) =  0.007° ≈ 0.00012 rad
    assign atan_table[14] = 16'sb0000_0000_0000_0001;   // atan(2^-14) =  0.004° ≈ 0.00006 rad

    //--------------------------------------------------------------------------
    // Main CORDIC computation
    // Implements rotation mode CORDIC algorithm with arctan LUT initialization
    //--------------------------------------------------------------------------
    always @(posedge clk or negedge rst_n) begin
        if (!rst_n) begin
            // Reset outputs and counter
            cos_out <= 0;
            sin_out <= 0;
            i       <= 0;

        end
        else begin
            case (state)
                //--------------------------------------------------------------
                // IDLE state: Wait for start signal and initialize CORDIC
                //--------------------------------------------------------------
                IDLE: begin
                    if (start) begin
                        x <= K;         // Initialize x with scaling factor
                        y <= 0;         // Initialize y to zero
                        z <= angle_in;  // Load input angle
                        i <= 0;         // Reset iteration counter
                    end
                end

                //--------------------------------------------------------------
                // ROTATE state: Perform CORDIC rotation iterations
                // Rotates vector (x,y) by angle z using micro-rotations
                //--------------------------------------------------------------
                ROTATE: begin
                    if (z[WL-1] == 0) begin
                        // Positive angle: rotate counter-clockwise
                        x <= x - (y >>> i);
                        y <= y + (x >>> i);
                        z <= z - atan_table[i];
                    end
                    else begin
                        // Negative angle: rotate clockwise
                        x <= x + (y >>> i);
                        y <= y - (x >>> i);
                        z <= z + atan_table[i];
                    end
                    i <= i + 1;  // Increment iteration counter
                end

                //--------------------------------------------------------------
                // DONE state: Latch final results
                //--------------------------------------------------------------
                DONE: begin
                    cos_out <= x;  // Final x is cosine
                    sin_out <= y;  // Final y is sine
                end
            endcase
        end
    end

    //--------------------------------------------------------------------------
    // Done flag generation
    // Indicates when computation is complete
    //--------------------------------------------------------------------------
    always @(posedge clk or negedge rst_n) begin
        if (!rst_n)
            done <= 0;
        else begin
            case (state)
                IDLE:    done <= 0;
                DONE:    done <= 1;
                default: done <= done;
            endcase
        end
    end

endmodule

tests/counter/src/counter.v
// Simple counter module for testing the parser
module counter#(
    parameter WIDTH = 16
)(
    input wire clk,
    input logic reset,
    input logic a_rst,
    output reg [WIDTH-1:0] count,
    output reg done
);
    wire [7:0] next_count;
    reg [7:0] my_value, my_new_value, sum, test;
    reg [3:0] my_vector_flop [0:1];
    localparam MY_PARAM = 0;

    assign next_count = count+1;

    always @(posedge clk or negedge a_rst) begin
        if (~a_rst) begin
            count <= MY_PARAM;
        end
        else begin
            if (reset) count <= 8'b0;
            else count <= next_count;
            done <= (count == 2**WIDTH-1);
        end
    end

    always @(posedge clk) begin
        my_vector_flop[0] <= 4'b1010;
        my_vector_flop[1] <= my_vector_flop[0];
    end

    always_comb begin
        my_value = 42+count;
        my_value = 43+my_value;
        my_new_value = 101*count;
        sum = 99+my_value;
        test = 1;
        if (my_vector_flop[0][0]) sum = my_value-my_new_value;
        else if (count==28+4*2) begin
            test = 8;
        end
        else begin
            sum = my_value+my_new_value;
            test = 42;
        end
    end

endmodule

/*
module counter_top(
    input wire clk,
    input logic reset,
    output reg [7:0] count
);
    wire [7:0] actual_count, count_plus_one;
    wire done;

    counter#(.WIDTH(8)) u_counter(.clk(clk), .reset(reset), .count(actual_count), .done(done));

    assign count_plus_one = actual_count + (done ? 2 : 3);

endmodule

module counter_top_wildcard(
    input wire clk,
    input logic reset,
    output reg [7:0] count
);
    counter#(.WIDTH(5)) u_counter(.*);
endmodule

// Simple adder module
module adder(
    input wire [7:0] a,
    input wire [7:0] b,
    output wire [8:0] sum
);

    assign sum = (82*a + b*b+48)*(-42+b*a);

endmodule

`include "file.vh"
*/

examples/sim_counter/verilog/tb.sv
`timescale 1ns/1ps

module async_data_driver#(type T, string name)(
    output T data,
    output bit done
);
    localparam string base_dir = "../../stimuli";

    typedef struct {
        int value;
        realtime timestamp;
    } async_type_t;

    function automatic void read_async_file(string filepath, output async_type_t data[]);
        int fd;
        string line;
        data = new[0];
        fd = $fopen(filepath, "r");

        if (fd == 0) begin
          $display("ERROR: Could not open file: %s", filepath);
          $finish;
        end

        while (1) begin
          int value;
          time timestamp;
          line = "";

          // Read line, break on EOF
          if ($fgets(line, fd) == 0) break;

          // Skip empty lines
          if (line.len() == 0) continue;

          // Skip comments (line starting with '#')
          if (line.tolower().substr(0, 0) == "#") continue;

          // Parse "time value"
          if ($sscanf(line, "%d %d", timestamp, value) == 2) begin
            data = new[data.size()+1](data);
            data[data.size()-1] = '{
              value: value,
              timestamp: timestamp
            };
          end
          else begin
            $display("WARNING: Could not parse line: %s", line);
          end
        end

        $fclose(fd);
    endfunction

    initial begin

        async_type_t signal_data[];

        string filepath = {base_dir, "/", name, ".txt"};

        read_async_file(filepath, signal_data);

        done = 0;

        foreach (signal_data[i]) begin
            $display("[%0t] Signal %s[%0d]: time=%0t(%0d) value=%0d", $realtime, name, i, signal_data[i].timestamp, int'(signal_data[i].timestamp), signal_data[i].value);
            #(signal_data[i].timestamp-$realtime) data = signal_data[i].value[0 +: $bits(T)];
        end
        done = 1;
    end
endmodule

module tb;
    localparam WIDTH = 8;

    logic clk;
    logic reset;
    logic a_rst;
    logic [WIDTH-1:0] count;
    logic done;

    counter#(.WIDTH(WIDTH)) dut (
        .clk(clk),
        .reset(reset),
        .a_rst(a_rst),
        .count(count),
        .done(done)
    );


    bit[2-1:0] dones;
    initial begin
        wait(&dones);
        $finish;
    end

    async_data_driver#(.T(logic), .name("clk")) u_clk_driver(.data(clk), .done(dones[0]));
    async_data_driver#(.T(logic), .name("a_rst")) u_a_rst_driver(.data(a_rst), .done(dones[1]));

    initial $timeformat(-9, -12, " ns", 10);

    // Waveform dump
    initial begin
        string database_name;
        if (!$value$plusargs("WAVES=%s", database_name)) begin
            $fatal(1, "Please provide WAVES database name");
        end
        $dumpfile(database_name);
        $dumpvars(0, tb_top);
    end

endmodule

examples/sim_counter/verilog/verilator/waves.vcd
$version Generated by VerilatedVcd $end
$timescale 1ps $end
 $scope module tb $end
  $var wire 32 1 WIDTH [31:0] $end
  $var wire 1 * clk $end
  $var wire 1 2 reset $end
  $var wire 1 + a_rst $end
  $var wire 8 # count [7:0] $end
  $var wire 1 $ done $end
  $var wire 2 , dones [1:0] $end
  $scope module dut $end
   $var wire 32 1 WIDTH [31:0] $end
   $var wire 1 * clk $end
   $var wire 1 2 reset $end
   $var wire 1 + a_rst $end
   $var wire 8 # count [7:0] $end
   $var wire 1 $ done $end
   $var wire 8 % next_count [7:0] $end
   $var wire 8 & my_value [7:0] $end
   $var wire 8 ' my_new_value [7:0] $end
   $var wire 8 ( sum [7:0] $end
   $var wire 8 ) test [7:0] $end
   $var wire 4 - my_vector_flop[0] [3:0] $end
   $var wire 4 . my_vector_flop[1] [3:0] $end
   $var wire 32 3 MY_PARAM [31:0] $end
  $upscope $end
  $scope module u_a_rst_driver $end
   $var wire 1 + data $end
   $var wire 1 / done $end
  $upscope $end
  $scope module u_clk_driver $end
   $var wire 1 * data $end
   $var wire 1 0 done $end
  $upscope $end
 $upscope $end
$enddefinitions $end


#0
b00000000 #
0$
b00000001 %
b01010101 &
b00000000 '
b01010101 (
b00101010 )
0*
0+
b00 ,
b0000 -
b0000 .
0/
00
b00000000000000000000000000001000 1
02
b00000000000000000000000000000000 3
#5000
1*
#10000
0*
#15000
1*
#20000
0*
#22000
1+
b10 ,
1/
#25000
b00000001 #
b00000010 %
b01010110 &
b01100101 '
b10111011 (
1*
#30000
0*
#35000
b00000010 #
b00000011 %
b01010111 &
b11001010 '
b00100001 (
1*
b0010 -
#40000
0*
#45000
b00000011 #
b00000100 %
b01011000 &
b00101111 '
b10000111 (
1*
b0100 -
b0010 .
#50000
0*
#55000
b00000100 #
b00000101 %
b01011001 &
b10010100 '
b11101101 (
1*
b0110 -
b0100 .
#60000
0*
#65000
b00000101 #
b00000110 %
b01011010 &
b11111001 '
b01010011 (
1*
b1000 -
b0110 .
#70000
0*
#75000
b00000110 #
b00000111 %
b01011011 &
b01011110 '
b10111001 (
1*
b1010 -
b1000 .
#80000
0*
#85000
b00000111 #
b00001000 %
b01011100 &
b11000011 '
b00011111 (
1*
b1100 -
b1010 .
#90000
0*
#95000
b00001000 #
b00001001 %
b01011101 &
b00101000 '
b10000101 (
1*
b11 ,
b1110 -
b1100 .
10
